myrmos/__init__.py
myrmos-0.0.1.dist-info/METADATA
myrmos-0.0.1.dist-info/WHEEL
myrmos-0.0.1.dist-info/top_level.txt
myrmos-0.0.1.dist-info/RECORD
